cloop/__init__.py
cloop-0.4.dist-info/METADATA
cloop-0.4.dist-info/WHEEL
cloop-0.4.dist-info/top_level.txt
cloop-0.4.dist-info/RECORD
